{
  "keybindings": {
    "Home": {
      "<Ctrl-c>": "Quit", // Quit the application
      "<Ctrl-z>": "Suspend" // Suspend the application
    },
  },
  "styles": {
    "Home": {
      "accent": "yellow",
      "accent_active": "lightyellow",
      "title": "bold lightyellow",
      "throbber": "lightyellow",
//      "accent": "cyan",
//      "accent_active": "lightcyan",
//      "title": "bold lightcyan",
//      "throbber": "lightcyan"
//      "accent": "magenta",
//      "accent_active": "lightmagenta",
//      "title": "bold lightmagenta",
//      "throbber": "lightmagenta"
    }
  }
}
